{
    "model_name": "Voting",
    "feature_sets": {
        "Scaled_PCA_50": {
            "fold_metrics": [
                {
                    "fold": 0,
                    "accuracy": 0.7191001769315022,
                    "precision": 0.657499742327709,
                    "recall": 0.7191001769315022,
                    "f1": 0.6768099093214284,
                    "auc": 0.6840232657766202
                },
                {
                    "fold": 1,
                    "accuracy": 0.7282837644283428,
                    "precision": 0.6708094154445364,
                    "recall": 0.7282837644283428,
                    "f1": 0.6865136945375317,
                    "auc": 0.7105887769827247
                },
                {
                    "fold": 2,
                    "accuracy": 0.732749178532311,
                    "precision": 0.674256979896159,
                    "recall": 0.732749178532311,
                    "f1": 0.6904674316446087,
                    "auc": 0.6974468619580967
                },
                {
                    "fold": 3,
                    "accuracy": 0.7346869997472407,
                    "precision": 0.6715910477229637,
                    "recall": 0.7346869997472407,
                    "f1": 0.6866164161903533,
                    "auc": 0.7165907700272705
                },
                {
                    "fold": 4,
                    "accuracy": 0.895357654393799,
                    "precision": 0.8631216269631945,
                    "recall": 0.895357654393799,
                    "f1": 0.8754187176541913,
                    "auc": 0.6902988476769256
                }
            ],
            "average_metrics": {
                "avg_accuracy": 0.7620355548066391,
                "avg_precision": 0.7074557624709126,
                "avg_recall": 0.7620355548066391,
                "avg_f1": 0.7231652338696226,
                "avg_auc": 0.6997897044843275
            }
        },
        "Scaled_Select50Best": {
            "fold_metrics": [
                {
                    "fold": 0,
                    "accuracy": 0.6988794338191928,
                    "precision": 0.652888416340656,
                    "recall": 0.6988794338191928,
                    "f1": 0.6725127172185006,
                    "auc": 0.7055044623346648
                },
                {
                    "fold": 1,
                    "accuracy": 0.7396579324290168,
                    "precision": 0.6918949310211141,
                    "recall": 0.7396579324290168,
                    "f1": 0.6968287084540438,
                    "auc": 0.7421997826184948
                },
                {
                    "fold": 2,
                    "accuracy": 0.7418485129328503,
                    "precision": 0.6855332117329148,
                    "recall": 0.7418485129328503,
                    "f1": 0.697964026603377,
                    "auc": 0.7062885046165938
                },
                {
                    "fold": 3,
                    "accuracy": 0.7374673519251832,
                    "precision": 0.6748642457512668,
                    "recall": 0.7374673519251832,
                    "f1": 0.6911890539584311,
                    "auc": 0.7239402979515953
                },
                {
                    "fold": 4,
                    "accuracy": 0.8967899570309209,
                    "precision": 0.863624431944437,
                    "recall": 0.8967899570309209,
                    "f1": 0.8763720341436875,
                    "auc": 0.6597370642097488
                }
            ],
            "average_metrics": {
                "avg_accuracy": 0.7629286376274328,
                "avg_precision": 0.7137610473580777,
                "avg_recall": 0.7629286376274328,
                "avg_f1": 0.726973308075608,
                "avg_auc": 0.7075340223462195
            }
        },
        "Scaled_LDA": {
            "fold_metrics": [
                {
                    "fold": 0,
                    "accuracy": 0.7235655910354706,
                    "precision": 0.6487102358751736,
                    "recall": 0.7235655910354706,
                    "f1": 0.6718374749450191,
                    "auc": 0.6730139970056651
                },
                {
                    "fold": 1,
                    "accuracy": 0.723986856516977,
                    "precision": 0.6583315742874845,
                    "recall": 0.723986856516977,
                    "f1": 0.67115000478086,
                    "auc": 0.6757634747443135
                },
                {
                    "fold": 2,
                    "accuracy": 0.7328334316286124,
                    "precision": 0.6641683245536694,
                    "recall": 0.7328334316286124,
                    "f1": 0.6807004193364883,
                    "auc": 0.6705747564410875
                },
                {
                    "fold": 3,
                    "accuracy": 0.7249978936725925,
                    "precision": 0.6570532758742006,
                    "recall": 0.7249978936725925,
                    "f1": 0.6777621082029629,
                    "auc": 0.6825813141312325
                },
                {
                    "fold": 4,
                    "accuracy": 0.895357654393799,
                    "precision": 0.8607023604368941,
                    "recall": 0.895357654393799,
                    "f1": 0.8724760237687621,
                    "auc": 0.7513492262143329
                }
            ],
            "average_metrics": {
                "avg_accuracy": 0.7601482854494902,
                "avg_precision": 0.6977931542054845,
                "avg_recall": 0.7601482854494902,
                "avg_f1": 0.7147852062068185,
                "avg_auc": 0.6906565537073264
            }
        }
    }
}